mcp_metricool/__init__.py
mcp_metricool/__main__.py
mcp_metricool/config.py
mcp_metricool/server.py
mcp_metricool/tools/__init__.py
mcp_metricool/tools/tools.py
mcp_metricool/utils/__init__.py
mcp_metricool/utils/utils.py
mcp_metricool-1.1.9.dist-info/METADATA
mcp_metricool-1.1.9.dist-info/WHEEL
mcp_metricool-1.1.9.dist-info/entry_points.txt
mcp_metricool-1.1.9.dist-info/licenses/LICENSE
mcp_metricool-1.1.9.dist-info/RECORD
