Metadata-Version: 2.4
Name: mcp-metricool
Version: 1.1.9
Summary: This is a Model Context Protocol (MCP) server for interacting with the Metricool API. It allows AI agents to access and analyze social media metrics and campaign data from your Metricool account.
Author-email: Laura Esteban <lauraesteban@metricool.com>, David Gonzalez <davidgonzalez@metricool.com>, Vicent Martí <vicentmarti@metricool.com>
License-File: LICENSE
Requires-Python: >=3.12
Requires-Dist: build>=1.2.2.post1
Requires-Dist: httpx>=0.28.1
Requires-Dist: mcp[cli]>=1.6.0
Requires-Dist: pytz>=2024.1
Requires-Dist: twine>=6.1.0
